pypexels/__init__.py
pypexels/pypexels.py
pypexels/examples/example_popular.py
pypexels/examples/example_search.py
pypexels/src/__init__.py
pypexels/src/curated.py
pypexels/src/errors.py
pypexels/src/liblogging.py
pypexels/src/models.py
pypexels/src/pexelspage.py
pypexels/src/popular.py
pypexels/src/rest.py
pypexels/src/search.py
pypexels/src/settings.py
pypexels_l5-1.0.0b4.dist-info/LICENSE
pypexels_l5-1.0.0b4.dist-info/WHEEL
pypexels_l5-1.0.0b4.dist-info/METADATA
pypexels_l5-1.0.0b4.dist-info/RECORD
